ws2s/__init__.py
ws2s/tcp_sockets.py
ws2s/websocket_server.py
ws2s/ws2s_config.py
ws2s/ws2s_server.py
ws2s/ws2sd.py
ws2s/resources/logging.conf
ws2s/resources/ws2sd
ws2s_python-2.1.5.dist-info/DESCRIPTION.rst
ws2s_python-2.1.5.dist-info/METADATA
ws2s_python-2.1.5.dist-info/RECORD
ws2s_python-2.1.5.dist-info/WHEEL
ws2s_python-2.1.5.dist-info/entry_points.txt
ws2s_python-2.1.5.dist-info/metadata.json
ws2s_python-2.1.5.dist-info/top_level.txt
