Metadata-Version: 2.0
Name: ws2s-python
Version: 2.1.5
Summary: transform websocket to socket, bring socket to browser-side js
Home-page: https://github.com/playay/ws2s
Author: chenyan
Author-email: chenyan@feling.net
License: MIT
Keywords: websocket tcp socket
Platform: UNKNOWN
Classifier: Development Status :: 5 - Production/Stable
Classifier: Environment :: No Input/Output (Daemon)
Classifier: Intended Audience :: Developers
Classifier: Topic :: Internet
Classifier: License :: OSI Approved :: MIT License
Classifier: Programming Language :: Python :: 2
Classifier: Programming Language :: Python :: 2.7
Classifier: Programming Language :: Python :: 3
Classifier: Programming Language :: Python :: 3.5
Classifier: Programming Language :: Python :: 3.6
Requires-Dist: gevent (>=1.2.2)
Requires-Dist: sshtunnel (>=0.1.3)
